odoo/addons/account_bank_statement_import_ofx/README.rst
odoo/addons/account_bank_statement_import_ofx/__init__.py
odoo/addons/account_bank_statement_import_ofx/__manifest__.py
odoo/addons/account_bank_statement_import_ofx/i18n/account_bank_statement_import_ofx.pot
odoo/addons/account_bank_statement_import_ofx/i18n/de.po
odoo/addons/account_bank_statement_import_ofx/i18n/es.po
odoo/addons/account_bank_statement_import_ofx/i18n/fi.po
odoo/addons/account_bank_statement_import_ofx/i18n/fr.po
odoo/addons/account_bank_statement_import_ofx/i18n/fr_CH.po
odoo/addons/account_bank_statement_import_ofx/i18n/gl.po
odoo/addons/account_bank_statement_import_ofx/i18n/lt_LT.po
odoo/addons/account_bank_statement_import_ofx/i18n/nb_NO.po
odoo/addons/account_bank_statement_import_ofx/i18n/nl.po
odoo/addons/account_bank_statement_import_ofx/i18n/pt_BR.po
odoo/addons/account_bank_statement_import_ofx/i18n/pt_PT.po
odoo/addons/account_bank_statement_import_ofx/i18n/sl.po
odoo/addons/account_bank_statement_import_ofx/static/description/icon.png
odoo/addons/account_bank_statement_import_ofx/tests/__init__.py
odoo/addons/account_bank_statement_import_ofx/tests/test_import_bank_statement.py
odoo/addons/account_bank_statement_import_ofx/tests/test_ofx_file/test_ofx.ofx
odoo/addons/account_bank_statement_import_ofx/tests/test_ofx_file/test_ofx_iban.ofx
odoo/addons/account_bank_statement_import_ofx/tests/test_ofx_file/test_ofx_wrong.ofx
odoo/addons/account_bank_statement_import_ofx/views/view_account_bank_statement_import.xml
odoo/addons/account_bank_statement_import_ofx/wizard/__init__.py
odoo/addons/account_bank_statement_import_ofx/wizard/account_bank_statement_import.py
odoo11_addon_account_bank_statement_import_ofx-11.0.1.0.0.99.dev3.dist-info/METADATA
odoo11_addon_account_bank_statement_import_ofx-11.0.1.0.0.99.dev3.dist-info/RECORD
odoo11_addon_account_bank_statement_import_ofx-11.0.1.0.0.99.dev3.dist-info/WHEEL
odoo11_addon_account_bank_statement_import_ofx-11.0.1.0.0.99.dev3.dist-info/top_level.txt
